ycm_cmake_modules/__init__.py
ycm_cmake_modules/share/YCM/3rdparty/CMakeRC.cmake
ycm_cmake_modules/share/YCM/3rdparty/COPYING.CMake-wiki
ycm_cmake_modules/share/YCM/3rdparty/COPYING.CMakeRC
ycm_cmake_modules/share/YCM/3rdparty/COPYING.Catch2
ycm_cmake_modules/share/YCM/3rdparty/COPYING.ECM
ycm_cmake_modules/share/YCM/3rdparty/COPYING.OVITO
ycm_cmake_modules/share/YCM/3rdparty/COPYING.UseLATEX
ycm_cmake_modules/share/YCM/3rdparty/COPYING.VTK
ycm_cmake_modules/share/YCM/3rdparty/COPYING.qgv
ycm_cmake_modules/share/YCM/3rdparty/COPYING.qt-gstreamer
ycm_cmake_modules/share/YCM/3rdparty/Catch.cmake
ycm_cmake_modules/share/YCM/3rdparty/CatchAddTests.cmake
ycm_cmake_modules/share/YCM/3rdparty/FindFFMPEG.cmake
ycm_cmake_modules/share/YCM/3rdparty/FindGLIB2.cmake
ycm_cmake_modules/share/YCM/3rdparty/FindGObject.cmake
ycm_cmake_modules/share/YCM/3rdparty/FindGStreamer.cmake
ycm_cmake_modules/share/YCM/3rdparty/FindGStreamerPluginsBase.cmake
ycm_cmake_modules/share/YCM/3rdparty/FindGraphviz.cmake
ycm_cmake_modules/share/YCM/3rdparty/FindOctave.cmake
ycm_cmake_modules/share/YCM/3rdparty/FindQCustomPlot.cmake
ycm_cmake_modules/share/YCM/3rdparty/FindUDev.cmake
ycm_cmake_modules/share/YCM/3rdparty/MacroFindGStreamerLibrary.cmake
ycm_cmake_modules/share/YCM/3rdparty/ParseAndAddCatchTests.cmake
ycm_cmake_modules/share/YCM/3rdparty/README.CMake-wiki
ycm_cmake_modules/share/YCM/3rdparty/README.CMakeRC
ycm_cmake_modules/share/YCM/3rdparty/README.Catch2
ycm_cmake_modules/share/YCM/3rdparty/README.ECM
ycm_cmake_modules/share/YCM/3rdparty/README.OVITO
ycm_cmake_modules/share/YCM/3rdparty/README.UseLATEX
ycm_cmake_modules/share/YCM/3rdparty/README.VTK
ycm_cmake_modules/share/YCM/3rdparty/README.qgv
ycm_cmake_modules/share/YCM/3rdparty/README.qt-gstreamer
ycm_cmake_modules/share/YCM/3rdparty/UseLATEX.cmake
ycm_cmake_modules/share/YCM/build-modules/BuildECM.cmake
ycm_cmake_modules/share/YCM/build-modules/BuildEigen3.cmake
ycm_cmake_modules-0.15.3.dist-info/METADATA
ycm_cmake_modules-0.15.3.dist-info/WHEEL
ycm_cmake_modules-0.15.3.dist-info/top_level.txt
ycm_cmake_modules-0.15.3.dist-info/RECORD
