Metadata-Version: 2.1
Name: ycm-cmake-modules
Version: 0.15.3
Summary: Extra CMake Modules for YARP and friends.
Home-page: http://robotology.github.io/ycm
Author: Diego Ferigo
Author-email: dgferigo@gmail.com
License: BSD
Project-URL: Tracker, https://github.com/robotology/ycm/issues
Project-URL: Documentation, http://robotology.github.io/ycm
Project-URL: Source, https://github.com/robotology/ycm
Keywords: cmake,cmake-modules,cmake-resources,build-tool,build-system,superbuild,yarp,robotics
Platform: any
Classifier: Development Status :: 5 - Production/Stable
Classifier: Operating System :: POSIX :: Linux
Classifier: Operating System :: MacOS
Classifier: Operating System :: Microsoft :: Windows
Classifier: Operating System :: OS Independent
Classifier: Framework :: Robot Framework
Classifier: Intended Audience :: Science/Research
Classifier: Intended Audience :: Developers
Classifier: Intended Audience :: Education
Classifier: Topic :: Software Development :: Build Tools
Classifier: Topic :: Software Development :: Code Generators
Classifier: Topic :: System :: Archiving :: Packaging
Classifier: License :: OSI Approved :: BSD License
Requires-Python: >=3.0
